{
  "id": "70d2a7ef-a2f7-4dbe-8297-13289f068183",
  "prevId": "6bd3c272-6b70-499a-90ad-15a5433a1c8d",
  "version": "7",
  "dialect": "postgresql",
  "tables": {
    "public.account": {
      "name": "account",
      "schema": "",
      "columns": {
        "userId": {
          "name": "userId",
          "type": "text",
          "primaryKey": false,
          "notNull": true
        },
        "type": {
          "name": "type",
          "type": "text",
          "primaryKey": false,
          "notNull": true
        },
        "provider": {
          "name": "provider",
          "type": "text",
          "primaryKey": false,
          "notNull": true
        },
        "providerAccountId": {
          "name": "providerAccountId",
          "type": "text",
          "primaryKey": false,
          "notNull": true
        },
        "refresh_token": {
          "name": "refresh_token",
          "type": "text",
          "primaryKey": false,
          "notNull": false
        },
        "access_token": {
          "name": "access_token",
          "type": "text",
          "primaryKey": false,
          "notNull": false
        },
        "expires_at": {
          "name": "expires_at",
          "type": "integer",
          "primaryKey": false,
          "notNull": false
        },
        "token_type": {
          "name": "token_type",
          "type": "text",
          "primaryKey": false,
          "notNull": false
        },
        "scope": {
          "name": "scope",
          "type": "text",
          "primaryKey": false,
          "notNull": false
        },
        "id_token": {
          "name": "id_token",
          "type": "text",
          "primaryKey": false,
          "notNull": false
        },
        "session_state": {
          "name": "session_state",
          "type": "text",
          "primaryKey": false,
          "notNull": false
        }
      },
      "indexes": {},
      "foreignKeys": {
        "account_userId_user_id_fk": {
          "name": "account_userId_user_id_fk",
          "tableFrom": "account",
          "tableTo": "user",
          "columnsFrom": [
            "userId"
          ],
          "columnsTo": [
            "id"
          ],
          "onDelete": "cascade",
          "onUpdate": "no action"
        }
      },
      "compositePrimaryKeys": {
        "account_provider_providerAccountId_pk": {
          "name": "account_provider_providerAccountId_pk",
          "columns": [
            "provider",
            "providerAccountId"
          ]
        }
      },
      "uniqueConstraints": {},
      "policies": {},
      "checkConstraints": {},
      "isRLSEnabled": false
    },
    "public.authenticator": {
      "name": "authenticator",
      "schema": "",
      "columns": {
        "credentialID": {
          "name": "credentialID",
          "type": "text",
          "primaryKey": false,
          "notNull": true
        },
        "userId": {
          "name": "userId",
          "type": "text",
          "primaryKey": false,
          "notNull": true
        },
        "providerAccountId": {
          "name": "providerAccountId",
          "type": "text",
          "primaryKey": false,
          "notNull": true
        },
        "credentialPublicKey": {
          "name": "credentialPublicKey",
          "type": "text",
          "primaryKey": false,
          "notNull": true
        },
        "counter": {
          "name": "counter",
          "type": "integer",
          "primaryKey": false,
          "notNull": true
        },
        "credentialDeviceType": {
          "name": "credentialDeviceType",
          "type": "text",
          "primaryKey": false,
          "notNull": true
        },
        "credentialBackedUp": {
          "name": "credentialBackedUp",
          "type": "boolean",
          "primaryKey": false,
          "notNull": true
        },
        "transports": {
          "name": "transports",
          "type": "text",
          "primaryKey": false,
          "notNull": false
        }
      },
      "indexes": {},
      "foreignKeys": {
        "authenticator_userId_user_id_fk": {
          "name": "authenticator_userId_user_id_fk",
          "tableFrom": "authenticator",
          "tableTo": "user",
          "columnsFrom": [
            "userId"
          ],
          "columnsTo": [
            "id"
          ],
          "onDelete": "cascade",
          "onUpdate": "no action"
        }
      },
      "compositePrimaryKeys": {
        "authenticator_userId_credentialID_pk": {
          "name": "authenticator_userId_credentialID_pk",
          "columns": [
            "userId",
            "credentialID"
          ]
        }
      },
      "uniqueConstraints": {
        "authenticator_credentialID_unique": {
          "name": "authenticator_credentialID_unique",
          "nullsNotDistinct": false,
          "columns": [
            "credentialID"
          ]
        }
      },
      "policies": {},
      "checkConstraints": {},
      "isRLSEnabled": false
    },
    "public.bank_accounts": {
      "name": "bank_accounts",
      "schema": "",
      "columns": {
        "id": {
          "name": "id",
          "type": "text",
          "primaryKey": true,
          "notNull": true
        },
        "userId": {
          "name": "userId",
          "type": "text",
          "primaryKey": false,
          "notNull": true
        },
        "requisitionId": {
          "name": "requisitionId",
          "type": "text",
          "primaryKey": false,
          "notNull": false
        },
        "institutionId": {
          "name": "institutionId",
          "type": "text",
          "primaryKey": false,
          "notNull": false
        },
        "institutionName": {
          "name": "institutionName",
          "type": "text",
          "primaryKey": false,
          "notNull": false
        },
        "iban": {
          "name": "iban",
          "type": "text",
          "primaryKey": false,
          "notNull": false
        },
        "accountId": {
          "name": "accountId",
          "type": "text",
          "primaryKey": false,
          "notNull": false
        },
        "accountName": {
          "name": "accountName",
          "type": "text",
          "primaryKey": false,
          "notNull": false
        },
        "balanceAmount": {
          "name": "balanceAmount",
          "type": "numeric(10, 2)",
          "primaryKey": false,
          "notNull": false
        },
        "balanceCurrency": {
          "name": "balanceCurrency",
          "type": "text",
          "primaryKey": false,
          "notNull": false
        },
        "ownerName": {
          "name": "ownerName",
          "type": "text",
          "primaryKey": false,
          "notNull": false
        },
        "linkStatus": {
          "name": "linkStatus",
          "type": "text",
          "primaryKey": false,
          "notNull": true,
          "default": "'active'"
        },
        "lastSyncAt": {
          "name": "lastSyncAt",
          "type": "timestamp",
          "primaryKey": false,
          "notNull": false
        },
        "createdAt": {
          "name": "createdAt",
          "type": "timestamp",
          "primaryKey": false,
          "notNull": true,
          "default": "now()"
        },
        "updatedAt": {
          "name": "updatedAt",
          "type": "timestamp",
          "primaryKey": false,
          "notNull": true,
          "default": "now()"
        }
      },
      "indexes": {
        "bank_accounts_user_id_idx": {
          "name": "bank_accounts_user_id_idx",
          "columns": [
            {
              "expression": "userId",
              "isExpression": false,
              "asc": true,
              "nulls": "last"
            }
          ],
          "isUnique": false,
          "concurrently": false,
          "method": "btree",
          "with": {}
        },
        "bank_accounts_requisition_id_idx": {
          "name": "bank_accounts_requisition_id_idx",
          "columns": [
            {
              "expression": "requisitionId",
              "isExpression": false,
              "asc": true,
              "nulls": "last"
            }
          ],
          "isUnique": false,
          "concurrently": false,
          "method": "btree",
          "with": {}
        }
      },
      "foreignKeys": {
        "bank_accounts_userId_user_id_fk": {
          "name": "bank_accounts_userId_user_id_fk",
          "tableFrom": "bank_accounts",
          "tableTo": "user",
          "columnsFrom": [
            "userId"
          ],
          "columnsTo": [
            "id"
          ],
          "onDelete": "cascade",
          "onUpdate": "no action"
        }
      },
      "compositePrimaryKeys": {},
      "uniqueConstraints": {},
      "policies": {},
      "checkConstraints": {},
      "isRLSEnabled": false
    },
    "public.session": {
      "name": "session",
      "schema": "",
      "columns": {
        "sessionToken": {
          "name": "sessionToken",
          "type": "text",
          "primaryKey": true,
          "notNull": true
        },
        "userId": {
          "name": "userId",
          "type": "text",
          "primaryKey": false,
          "notNull": true
        },
        "expires": {
          "name": "expires",
          "type": "timestamp",
          "primaryKey": false,
          "notNull": true
        }
      },
      "indexes": {},
      "foreignKeys": {
        "session_userId_user_id_fk": {
          "name": "session_userId_user_id_fk",
          "tableFrom": "session",
          "tableTo": "user",
          "columnsFrom": [
            "userId"
          ],
          "columnsTo": [
            "id"
          ],
          "onDelete": "cascade",
          "onUpdate": "no action"
        }
      },
      "compositePrimaryKeys": {},
      "uniqueConstraints": {},
      "policies": {},
      "checkConstraints": {},
      "isRLSEnabled": false
    },
    "public.token": {
      "name": "token",
      "schema": "",
      "columns": {
        "id": {
          "name": "id",
          "type": "text",
          "primaryKey": true,
          "notNull": true
        },
        "access_token": {
          "name": "access_token",
          "type": "text",
          "primaryKey": false,
          "notNull": true
        },
        "refresh_token": {
          "name": "refresh_token",
          "type": "text",
          "primaryKey": false,
          "notNull": true
        },
        "created_at": {
          "name": "created_at",
          "type": "timestamp",
          "primaryKey": false,
          "notNull": false,
          "default": "now()"
        },
        "expires_at": {
          "name": "expires_at",
          "type": "integer",
          "primaryKey": false,
          "notNull": true
        }
      },
      "indexes": {},
      "foreignKeys": {},
      "compositePrimaryKeys": {},
      "uniqueConstraints": {},
      "policies": {},
      "checkConstraints": {},
      "isRLSEnabled": false
    },
    "public.user": {
      "name": "user",
      "schema": "",
      "columns": {
        "id": {
          "name": "id",
          "type": "text",
          "primaryKey": true,
          "notNull": true
        },
        "name": {
          "name": "name",
          "type": "text",
          "primaryKey": false,
          "notNull": false
        },
        "email": {
          "name": "email",
          "type": "text",
          "primaryKey": false,
          "notNull": false
        },
        "emailVerified": {
          "name": "emailVerified",
          "type": "timestamp",
          "primaryKey": false,
          "notNull": false
        },
        "image": {
          "name": "image",
          "type": "text",
          "primaryKey": false,
          "notNull": false
        }
      },
      "indexes": {},
      "foreignKeys": {},
      "compositePrimaryKeys": {},
      "uniqueConstraints": {
        "user_email_unique": {
          "name": "user_email_unique",
          "nullsNotDistinct": false,
          "columns": [
            "email"
          ]
        }
      },
      "policies": {},
      "checkConstraints": {},
      "isRLSEnabled": false
    },
    "public.verificationToken": {
      "name": "verificationToken",
      "schema": "",
      "columns": {
        "identifier": {
          "name": "identifier",
          "type": "text",
          "primaryKey": false,
          "notNull": true
        },
        "token": {
          "name": "token",
          "type": "text",
          "primaryKey": false,
          "notNull": true
        },
        "expires": {
          "name": "expires",
          "type": "timestamp",
          "primaryKey": false,
          "notNull": true
        }
      },
      "indexes": {},
      "foreignKeys": {},
      "compositePrimaryKeys": {
        "verificationToken_identifier_token_pk": {
          "name": "verificationToken_identifier_token_pk",
          "columns": [
            "identifier",
            "token"
          ]
        }
      },
      "uniqueConstraints": {},
      "policies": {},
      "checkConstraints": {},
      "isRLSEnabled": false
    }
  },
  "enums": {},
  "schemas": {},
  "sequences": {},
  "roles": {},
  "policies": {},
  "views": {},
  "_meta": {
    "columns": {},
    "schemas": {},
    "tables": {}
  }
}